woc/__init__.py
woc/__version__.py
woc/_compat.py
woc/appdirs.py
woc/cmdline.py
woc/config.py
woc/config_source.py
woc/decorator.py
woc/dict_config_source.py
woc/downloader.py
woc/file_config_source.py
woc/get_local_ip_address.py
woc/helpers.py
woc/latexcore.py
woc/latexdocx.py
woc/latexfortran.py
woc/locations.py
woc/math2latex.py
woc/patterns.py
woc/shell.py
woc/source.py
woc/tree.py
woc/resources/Alias.md
woc/resources/GitTutorials.md
woc/resources/Philosophy.md
woc/scripts/__init__.py
woc/scripts/aptinstall.sh
woc/scripts/clean.sh
woc/scripts/create.sh
woc/scripts/delete.sh
woc/scripts/deploy.sh
woc/scripts/install.sh
woc/scripts/installmysql.sh
woc/scripts/npminstall.sh
woc/scripts/publish.sh
woc/scripts/requirements.sh
woc/scripts/run.sh
woc/scripts/service.sh
woc/scripts/setnotebook.sh
woc-2.0.1.data/data/LICENSE
woc-2.0.1.dist-info/LICENSE
woc-2.0.1.dist-info/METADATA
woc-2.0.1.dist-info/WHEEL
woc-2.0.1.dist-info/entry_points.txt
woc-2.0.1.dist-info/top_level.txt
woc-2.0.1.dist-info/RECORD
