Metadata-Version: 2.1
Name: woc
Version: 2.0.1
Summary: WOC, this tool is amazing🤣🤣😄😆
Home-page: https://github.com/szj2ys/woc
Author: szj
Author-email: szj2ys@qq.com
License: MIT
Classifier: Development Status :: 1 - Planning
Classifier: Environment :: Console
Classifier: License :: OSI Approved :: MIT License
Classifier: Programming Language :: Python :: 3
Requires-Python: >=3.6.0
License-File: LICENSE
Requires-Dist: pipenv
Requires-Dist: dynaconf
Requires-Dist: pandas
Requires-Dist: tqdm
Requires-Dist: rich
Requires-Dist: click
Requires-Dist: click-help-colors
Requires-Dist: shellingham
Requires-Dist: tomlkit
Requires-Dist: yapf
Requires-Dist: autoflake
Requires-Dist: twine
